{
  "id": "discovercommon",
  "cardName": "The Encyclopedia",
  "baseCard": "discovercommon",
  "cardUpgraded": 3,
  "upgradedFrom": "discovercommon",
  "cardRarity": 0,
  "cardType": 0,
  "cardClass": -1,
  "energyCost": 0,
  "playable": true,
  "targetSide": 3,
  "effectRepeat": 1,
  "addCard": 1,
  "addCardChoose": 6,
  "addCardFrom": 2,
  "addCardPlace": 5,
  "addCardReducedCost": 0,
  "addCardVanish": true,
  "showInTome": true,
  "vanish": false,
  "autoplayDraw": false,
  "innate": true,
  "imageFileName": "TheEncyclopedia.png"
}